{
  "/_not-found/page": "app/_not-found/page.js",
  "/page": "app/page.js",
  "/(dashboard)/calendar/page": "app/(dashboard)/calendar/page.js",
  "/(dashboard)/dashboard/page": "app/(dashboard)/dashboard/page.js",
  "/(dashboard)/history/page": "app/(dashboard)/history/page.js",
  "/(dashboard)/model-health/page": "app/(dashboard)/model-health/page.js",
  "/(dashboard)/niches/page": "app/(dashboard)/niches/page.js",
  "/(dashboard)/predict/page": "app/(dashboard)/predict/page.js",
  "/(dashboard)/stories/page": "app/(dashboard)/stories/page.js",
  "/(dashboard)/suggest/page": "app/(dashboard)/suggest/page.js"
}